photofolio/__init__.py
photofolio/admin.py
photofolio/apps.py
photofolio/forms.py
photofolio/models.py
photofolio/urls.py
photofolio/views.py
photofolio/static/photofolio/css/main.css
photofolio/static/photofolio/img/apple-touch-icon.png
photofolio/static/photofolio/img/favicon.png
photofolio/static/photofolio/img/profile-img.jpg
photofolio/static/photofolio/img/gallery/gallery-1.jpg
photofolio/static/photofolio/img/gallery/gallery-10.jpg
photofolio/static/photofolio/img/gallery/gallery-11.jpg
photofolio/static/photofolio/img/gallery/gallery-12.jpg
photofolio/static/photofolio/img/gallery/gallery-13.jpg
photofolio/static/photofolio/img/gallery/gallery-14.jpg
photofolio/static/photofolio/img/gallery/gallery-15.jpg
photofolio/static/photofolio/img/gallery/gallery-16.jpg
photofolio/static/photofolio/img/gallery/gallery-2.jpg
photofolio/static/photofolio/img/gallery/gallery-3.jpg
photofolio/static/photofolio/img/gallery/gallery-4.jpg
photofolio/static/photofolio/img/gallery/gallery-5.jpg
photofolio/static/photofolio/img/gallery/gallery-6.jpg
photofolio/static/photofolio/img/gallery/gallery-7.jpg
photofolio/static/photofolio/img/gallery/gallery-8.jpg
photofolio/static/photofolio/img/gallery/gallery-9.jpg
photofolio/static/photofolio/img/portfolio/app-1.jpg
photofolio/static/photofolio/img/portfolio/books-1.jpg
photofolio/static/photofolio/img/portfolio/branding-1.jpg
photofolio/static/photofolio/img/portfolio/product-1.jpg
photofolio/static/photofolio/img/testimonials/testimonials-1.jpg
photofolio/static/photofolio/img/testimonials/testimonials-2.jpg
photofolio/static/photofolio/img/testimonials/testimonials-3.jpg
photofolio/static/photofolio/img/testimonials/testimonials-4.jpg
photofolio/static/photofolio/img/testimonials/testimonials-5.jpg
photofolio/static/photofolio/js/main.js
photofolio/static/photofolio/scss/_footer.scss
photofolio/static/photofolio/scss/_general.scss
photofolio/static/photofolio/scss/_header.scss
photofolio/static/photofolio/scss/_hero.scss
django_photofolio_ds-0.3.6.dist-info/LICENSE
django_photofolio_ds-0.3.6.dist-info/METADATA
django_photofolio_ds-0.3.6.dist-info/WHEEL
django_photofolio_ds-0.3.6.dist-info/top_level.txt
django_photofolio_ds-0.3.6.dist-info/RECORD
